{
  "000858": {
    "code": "000858",
    "cost_price": 13.027798591040831,
    "current_shares": 1400,
    "original_shares": 0,
    "highest_price": 13.119032397593246,
    "entry_date": "",
    "warning_reduced": true,
    "warning_trigger_date": "20260528",
    "warning_reason": "B2:量价背离",
    "b1_needs_nextday_check": false,
    "b1_trigger_date": "",
    "b1_additional_reduced": false,
    "confirm_reduced": false,
    "confirm_trigger_date": "",
    "confirm_reason": "",
    "cleared": false,
    "cleared_date": "",
    "rebound_restored": false,
    "reduction_volume": 500
  },
  "600036": {
    "code": "600036",
    "cost_price": 15.785512456003673,
    "current_shares": 0,
    "original_shares": 0,
    "highest_price": 15.785512456003673,
    "entry_date": "",
    "warning_reduced": false,
    "warning_trigger_date": "",
    "warning_reason": "",
    "b1_needs_nextday_check": false,
    "b1_trigger_date": "",
    "b1_additional_reduced": false,
    "confirm_reduced": false,
    "confirm_trigger_date": "",
    "confirm_reason": "",
    "cleared": true,
    "cleared_date": "20260528",
    "rebound_restored": false,
    "reduction_volume": 0
  },
  "600519": {
    "code": "600519",
    "cost_price": 10.760922134400628,
    "current_shares": 0,
    "original_shares": 0,
    "highest_price": 10.847215773566639,
    "entry_date": "",
    "warning_reduced": false,
    "warning_trigger_date": "",
    "warning_reason": "",
    "b1_needs_nextday_check": false,
    "b1_trigger_date": "",
    "b1_additional_reduced": false,
    "confirm_reduced": false,
    "confirm_trigger_date": "",
    "confirm_reason": "",
    "cleared": true,
    "cleared_date": "20260529",
    "rebound_restored": false,
    "reduction_volume": 0
  },
  "601318": {
    "code": "601318",
    "cost_price": 14.240440048684166,
    "current_shares": 0,
    "original_shares": 0,
    "highest_price": 14.240440048684166,
    "entry_date": "",
    "warning_reduced": false,
    "warning_trigger_date": "",
    "warning_reason": "",
    "b1_needs_nextday_check": false,
    "b1_trigger_date": "",
    "b1_additional_reduced": false,
    "confirm_reduced": false,
    "confirm_trigger_date": "",
    "confirm_reason": "",
    "cleared": true,
    "cleared_date": "20260529",
    "rebound_restored": false,
    "reduction_volume": 0
  }
}